Metadata-Version: 1.0
Name: wybrobin-aa
Version: 1.0.0
Summary: aa test
Home-page: https://github.com/wybrobin/packtest
Author: wyb
Author-email: wyb_robin@163.com
License: MIT Licence
Keywords: pip,aa
Platform: any
